flmakesetup
templates
