Metadata-Version: 1.1
Name: flmakesetup
Version: 0.0.8
Summary: easy create setup.py
Home-page: https://github.com/float1251/flmakesetup
Author: takahrio iwatani
Author-email: taka.05022002@gmail.com
License: UNKNOWN
Platform: UNKNOWN
Classifier: Development Status :: 3 - Alpha
Classifier: Programming Language :: Python :: 3
Classifier: License :: OSI Approved :: MIT License
